CnyZodiac.py
ChineseNewYear_Zodiac-1.0.0.dist-info/LICENSE
ChineseNewYear_Zodiac-1.0.0.dist-info/METADATA
ChineseNewYear_Zodiac-1.0.0.dist-info/WHEEL
ChineseNewYear_Zodiac-1.0.0.dist-info/top_level.txt
ChineseNewYear_Zodiac-1.0.0.dist-info/RECORD
