Metadata-Version: 2.1
Name: ChineseNewYear-Zodiac
Version: 1.0.0
Summary: A simple Python package to find Chinese New Year and Chinese Zodiac
Author-email: Nicolas Flandrois <nicolas.dev@flandrois.com>
Maintainer-email: Nicolas Flandrois <nicolas.dev@flandrois.com>
Project-URL: Homepage, https://github.com/NicolasFlandrois/Chinese-New-Year-and-Zodiac
Project-URL: GitHub, https://github.com/NicolasFlandrois/Chinese-New-Year-and-Zodiac
Classifier: Programming Language :: Python :: 3
Classifier: License :: OSI Approved :: MIT License
Classifier: Operating System :: OS Independent
Requires-Python: >=3.7
License-File: LICENSE
Requires-Dist: astral
